__init__.py
__version__.py
korean_news_crawler/chosun.py
korean_news_crawler/donga.py
korean_news_crawler/hankook.py
korean_news_crawler/hankyoreh.py
korean_news_crawler/joongang.py
korean_news_crawler/kukmin.py
korean_news_crawler/kyunghyang.py
korean_news_crawler/munhwa.py
korean_news_crawler/naeil.py
korean_news_crawler/news.py
korean_news_crawler/segye.py
korean_news_crawler/seoul.py
korean_news_crawler/synonym_dict.py
korean_news_crawler-1.0.5.dist-info/METADATA
korean_news_crawler-1.0.5.dist-info/WHEEL
korean_news_crawler-1.0.5.dist-info/top_level.txt
korean_news_crawler-1.0.5.dist-info/RECORD
