Metadata-Version: 2.1
Name: korean-news-crawler
Version: 1.0.5
Summary: Python Library for Crawling Top 10 Korean News and Providing Synonym Dictionary
Home-page: https://github.com/Indigo-Coder-github/Korean_News_Crawler
Author: Indigo-Coder
Author-email: hjs40111@gmail.com
Project-URL: Bug Tracker, https://github.com/Indigo-Coder-github/Korean_News_Crawler/issues
Classifier: Programming Language :: Python :: 3
Classifier: Operating System :: OS Independent
Requires-Python: >=3.8
Requires-Dist: BeautifulSoup4
Requires-Dist: selenium
